[
  {
    "time": "01:41",
    "quote_first": "Raffles, without a stitch of clothing on his body, but with a glass phial, corked with cotton-wool, between his teeth, and a tiny screw-driver behind his ear, squirmed feet first through the ventilator over his berth; and it was ",
    "quote_time_case": "nineteen minutes to two",
    "quote_last": " when he returned, head first, with the phial still between his teeth and the cotton-wool rammed home to still the rattling of that which lay like a great gray bean within.",
    "title": "The Amateur Cracksman",
    "author": "E.W. Hornung",
    "sfw": "no"
  }
]