[
  {
    "time": "04:31",
    "quote_first": "As Miss Nichol walked along the corridor, she checked her watch. It was ",
    "quote_time_case": "4:31 A.M.",
    "quote_last": " She took the stairs down to the fifth floor and made her way to the nursery.",
    "title": "Sons of Fortune",
    "author": "Jeffrey Archer",
    "sfw": "yes"
  },
  {
    "time": "04:31",
    "quote_first": "An earthquake hit Los Angeles at ",
    "quote_time_case": "4:31",
    "quote_last": " this morning and the images began arriving via CNN right away.",
    "title": "Microserfs",
    "author": "Douglas Coupland",
    "sfw": "yes"
  }
]