[
  {
    "time": "08:27",
    "quote_first": "On arriving at platform one at Sevenoaks station, he would purchase a copy of the Daily Express before boarding the ",
    "quote_time_case": "8:27",
    "quote_last": " to Cannon Street.",
    "title": "Broken Routine",
    "author": "Jeffrey Archer",
    "sfw": "yes"
  },
  {
    "time": "08:27",
    "quote_first": "Even dawdling over breakfast with my mother just killed an hour, and though I hadn’t planned to be at Marge’s until nine, I was knocking on her door at ",
    "quote_time_case": "twenty-seven minutes past eight",
    "quote_last": ".",
    "title": "Fatally Frosted",
    "author": "Jessica Beck",
    "sfw": "yes"
  },
  {
    "time": "08:27",
    "quote_first": "The lecture was to be given tomorrow, and it was now ",
    "quote_time_case": "almost eight-thirty",
    "quote_last": ".",
    "title": "A Confederacy of Dunces",
    "author": "John Kennedy Toole",
    "sfw": "yes"
  }
]