[
  {
    "time": "17:01",
    "quote_first": "At ",
    "quote_time_case": "one minute past five",
    "quote_last": ", Beth left the museum, hailed a taxi and, after giving the driver her address, sat in the back surrounded by boxes and unashamedly shed a tear.",
    "title": "Next in Line",
    "author": "Jeffrey Archer",
    "sfw": "yes"
  },
  {
    "time": "17:01",
    "quote_first": "",
    "quote_time_case": "One minute after five",
    "quote_last": ". The seated guests were told that the ceremony would begin shortly. A little more patience was required.",
    "title": "Trouble & Triumph: A Novel of Power & Beauty",
    "author": "Tip \"T.I.\" Harris with David Ritz",
    "sfw": "yes"
  }
]