[
  {
    "time": "20:59",
    "quote_first": "However, you will go no farther than two miles from the barracks, you will behave in a manner that befits a Royal Fusilier and you will report back to the guardroom sober as a judge at ",
    "quote_time_case": "one minute before nine",
    "quote_last": ".",
    "title": "As The Crow Flies",
    "author": "Jeffrey Archer",
    "sfw": "yes"
  },
  {
    "time": "20:59",
    "quote_first": "Normally an assistant would have put [the television] on for him at ",
    "quote_time_case": "one minute to nine",
    "quote_last": ". He sat watching a Nigerian woman give a talk on dressmaking, followed by the weather forecast man who supplied Eduardo with the revealing information that the temperature would continue to be hot for the next month.",
    "title": "The Coup",
    "author": "Jeffrey Archer",
    "sfw": "yes"
  },
  {
    "time": "20:59",
    "quote_first": "“Well, what an amazing culinary experience,” Eva said at ",
    "quote_time_case": "8:59 p.m.",
    "quote_last": ", when Prager’s car parked in front of her apartment.",
    "title": "Kitchens of the Great Midwest",
    "author": "J. Ryan Stradal",
    "sfw": "yes"
  }
]