[
  {
    "time": "21:45",
    "quote_first": "Hattie would certainly return soon. She wouldn&rsquo;t leave a room for long while Char occupied it.<br />My dance ended as the clock struck ",
    "quote_time_case": "the quarter before ten",
    "quote_last": ".",
    "title": "Ella Enchanted",
    "author": "Gail Carson Levine",
    "sfw": "yes"
  },
  {
    "time": "21:45",
    "quote_first": "But for some unfathomable reason-birth, death, the end of the universe and all things available to man-Cody Menhoff&rsquo;s was closed at ",
    "quote_time_case": "9:45 PM",
    "quote_last": " on a Thursday&hellip;",
    "title": "Riven Rock",
    "author": "T. C. Boyle",
    "sfw": "yes"
  }
]